rovpy/rovpy.py
rovpy-0.0.7.dist-info/LICENSE
rovpy-0.0.7.dist-info/METADATA
rovpy-0.0.7.dist-info/WHEEL
rovpy-0.0.7.dist-info/top_level.txt
rovpy-0.0.7.dist-info/RECORD
