Metadata-Version: 2.1
Name: rovpy
Version: 0.0.7
Summary: Ardusub based Rov Library
Home-page: https://github.com/enisgetmez
Author: Enis Getmez
Author-email: enis@enisgetmez.com
License: MIT
Platform: UNKNOWN
Classifier: License :: OSI Approved :: MIT License
Classifier: Programming Language :: Python :: 3
Classifier: Programming Language :: Python :: 3.6
Classifier: Programming Language :: Python :: 3.7
Classifier: Programming Language :: Python :: 3.8
